basic_agent_chat_loop/__init__.py
basic_agent_chat_loop/__main__.py
basic_agent_chat_loop/chat_config.py
basic_agent_chat_loop/chat_loop.py
basic_agent_chat_loop/cli.py
basic_agent_chat_loop/notification.wav
basic_agent_chat_loop/components/__init__.py
basic_agent_chat_loop/components/agent_loader.py
basic_agent_chat_loop/components/alias_manager.py
basic_agent_chat_loop/components/audio_notifier.py
basic_agent_chat_loop/components/command_router.py
basic_agent_chat_loop/components/config_wizard.py
basic_agent_chat_loop/components/dependency_manager.py
basic_agent_chat_loop/components/display_manager.py
basic_agent_chat_loop/components/error_messages.py
basic_agent_chat_loop/components/harmony_processor.py
basic_agent_chat_loop/components/input_handler.py
basic_agent_chat_loop/components/response_renderer.py
basic_agent_chat_loop/components/response_streamer.py
basic_agent_chat_loop/components/session_manager.py
basic_agent_chat_loop/components/session_persister.py
basic_agent_chat_loop/components/session_restorer.py
basic_agent_chat_loop/components/session_state.py
basic_agent_chat_loop/components/streaming_event_parser.py
basic_agent_chat_loop/components/template_manager.py
basic_agent_chat_loop/components/token_tracker.py
basic_agent_chat_loop/components/ui_components.py
basic_agent_chat_loop/components/usage_extractor.py
basic_agent_chat_loop-1.10.0.dist-info/licenses/LICENSE
basic_agent_chat_loop-1.10.0.dist-info/METADATA
basic_agent_chat_loop-1.10.0.dist-info/WHEEL
basic_agent_chat_loop-1.10.0.dist-info/entry_points.txt
basic_agent_chat_loop-1.10.0.dist-info/top_level.txt
basic_agent_chat_loop-1.10.0.dist-info/RECORD
