Metadata-Version: 2.4
Name: basic-agent-chat-loop
Version: 1.10.0
Summary: Feature-rich interactive CLI for AWS Strands agents with token tracking, prompt templates, aliases, and configuration
Author-email: Wes <unseriousai@gmail.com>
Maintainer-email: Wes <unseriousai@gmail.com>
Project-URL: Homepage, https://github.com/Open-Agent-Tools/Basic-Agent-Chat-Loop
Project-URL: Repository, https://github.com/Open-Agent-Tools/Basic-Agent-Chat-Loop
Project-URL: Bug Tracker, https://github.com/Open-Agent-Tools/Basic-Agent-Chat-Loop/issues
Keywords: agent,chat,loop,cli
Classifier: Development Status :: 5 - Production/Stable
Classifier: Environment :: Console
Classifier: Intended Audience :: Developers
Classifier: Natural Language :: English
Classifier: Operating System :: OS Independent
Classifier: Programming Language :: Python :: 3
Classifier: Programming Language :: Python :: 3.9
Classifier: Programming Language :: Python :: 3.10
Classifier: Programming Language :: Python :: 3.11
Classifier: Programming Language :: Python :: 3.12
Classifier: Topic :: Communications :: Chat
Classifier: Topic :: Scientific/Engineering :: Artificial Intelligence
Classifier: Topic :: Software Development :: Libraries :: Application Frameworks
Classifier: Typing :: Typed
Requires-Python: >=3.10
License-File: LICENSE
Requires-Dist: pyyaml>=6.0.3
Requires-Dist: rich>=14.2.0
Requires-Dist: pyreadline3>=3.5.4; platform_system == "Windows"
Requires-Dist: pyperclip>=1.11.0
Requires-Dist: openai-harmony>=0.0.8
Provides-Extra: dev
Requires-Dist: pytest>=9.0.2; extra == "dev"
Requires-Dist: pytest-cov>=7.0.0; extra == "dev"
Requires-Dist: black>=25.12.0; extra == "dev"
Requires-Dist: ruff>=0.14.10; extra == "dev"
Requires-Dist: mypy>=1.19.1; extra == "dev"
Provides-Extra: windows
Provides-Extra: bedrock
Requires-Dist: anthropic-bedrock>=0.8.0; extra == "bedrock"
Dynamic: license-file
